mlsquare/__init__.py
mlsquare/base.py
mlsquare/core.py
mlsquare/adapters/__init__.py
mlsquare/adapters/sklearn.py
mlsquare/architectures/__init__.py
mlsquare/architectures/irt.py
mlsquare/architectures/sklearn.py
mlsquare/layers/__init__.py
mlsquare/layers/deepctr.py
mlsquare/layers/keras.py
mlsquare/losses/__init__.py
mlsquare/losses/keras.py
mlsquare/models/__init__.py
mlsquare/models/irt.py
mlsquare/optmizers/__init__.py
mlsquare/optmizers/arch_search.py
mlsquare/optmizers/tune.py
mlsquare/utils/__init__.py
mlsquare/utils/correlations.py
mlsquare/utils/functions.py
mlsquare-0.2.2.1.dist-info/AUTHORS.rst
mlsquare-0.2.2.1.dist-info/LICENSE.txt
mlsquare-0.2.2.1.dist-info/METADATA
mlsquare-0.2.2.1.dist-info/WHEEL
mlsquare-0.2.2.1.dist-info/top_level.txt
mlsquare-0.2.2.1.dist-info/RECORD
