Metadata-Version: 2.1
Name: mlsquare
Version: 0.2.2.1
Summary: Machine Learning for Machine Learning
Home-page: https://mlsquare.org
Author: MLSquare
Author-email: info@mlsquare.org
License: MIT
Platform: any
Classifier: Development Status :: 5 - Production/Stable
Classifier: Intended Audience :: Developers
Classifier: License :: OSI Approved :: MIT License
Classifier: Programming Language :: Python
Classifier: Topic :: Scientific/Engineering :: Artificial Intelligence
Classifier: Topic :: Scientific/Engineering :: Mathematics
Classifier: Topic :: Software Development :: Libraries :: Python Modules
Requires-Python: >=3.6
License-File: LICENSE.txt
License-File: AUTHORS.rst
Requires-Dist: dict-deep
Requires-Dist: hyperopt
Requires-Dist: deepctr
Requires-Dist: numpy
Requires-Dist: onnx
Requires-Dist: onnxmltools
Requires-Dist: pandas
Requires-Dist: pickleshare
Requires-Dist: scikit-learn
Requires-Dist: scipy
Requires-Dist: Theano
Requires-Dist: tensorflow (>=2.5.1)
Requires-Dist: ray[tune]
Requires-Dist: matplotlib
Requires-Dist: networkx
Requires-Dist: torch
Requires-Dist: tf2onnx
Provides-Extra: testing
Requires-Dist: pytest ; extra == 'testing'
Requires-Dist: pytest-cov ; extra == 'testing'
